source/input_mux.v
`timescale 1ns / 1ps

module input_mux #(
    parameter DATA_WIDTH = 8
)(
    input [DATA_WIDTH-1:0] in1,
    input [DATA_WIDTH-1:0] in2,
    input [1:0] sel,
    output [DATA_WIDTH-1:0] op
    );
    assign op = (sel == 2'b01) ? in1 : ((sel == 2'b00) ? in2: 0);
endmodule

source/shift_register.v
`timescale 1ns/1ps

module shift_register #(
    parameter DATA_WIDTH = 16,
    parameter size = 3
)(
    input clk, ce, rst,
    input [DATA_WIDTH-1:0] data_in,
    output [DATA_WIDTH-1:0] data_out
);
    reg [DATA_WIDTH-1:0] tmp[size-1:0];
    
    generate
        genvar l;
        for (l = 0; l < size; l = l + 1) begin
            always @(posedge clk) begin
                if (rst) begin
                    tmp[l] <= 'd0;
                end
                else if (ce) begin
                    if (l == 'd0) begin
                        tmp[l] <= data_in;  
                    end
                    else begin
                        tmp[l] <= tmp[l-1];
                    end
                end
            end
        end
    assign data_out = tmp[size-1];
    endgenerate
    
endmodule

source/max_reg.v
`timescale 1ns / 1ps
module max_reg #(parameter DATA_WIDTH = 16) (
    input clk,
    input ce,
    input [DATA_WIDTH-1:0] data_in,
    input rst_m,
    input master_rst,
    output reg [DATA_WIDTH-1:0] reg_op
    );

    always@(posedge clk) 
    begin
    	if(master_rst)
    		reg_op <= 0;
    	else 
        begin
            if(ce) 
            begin
		   	  if(rst_m) begin
		    	 reg_op <=0;
		      end
		      else begin
		    	 reg_op <= data_in;
			 end
		    end
		end
	end
endmodule

source/comparator2.v
`timescale 1ns / 1ps

module comparator2 #(
    parameter DATA_WIDTH = 16,
    parameter POOL_TYPE = 1
    )(
    input ce,
    input [DATA_WIDTH-1:0] in1,
    input [DATA_WIDTH-1:0] in2,
    output [DATA_WIDTH-1:0] comp_op
    ); 
    reg [DATA_WIDTH-1:0] temp;
    assign comp_op = ce ? temp : 'd0;

    always@(*)
    begin
        if(POOL_TYPE == 0)
        begin
            temp = in1 + in2;        
        end
        else begin
            temp = (in1 > in2) ? in1 : in2;
        end
    end
endmodule

source/control_logic2.v
`timescale 1ns / 1ps

module control_logic2 #(
    parameter INPUT_SIZE = 9'h004,   // Total number of rows in the input
    parameter POOL_SIZE = 9'h002    // Pooling size (both width and height)
)(
    input clk,             
    input master_rst,       
    input ce,            
    output reg [1:0] sel, 
    output reg rst_m,     
    output reg op_en,      
    output reg load_sr,    
    output reg global_rst,  
    output reg end_op       
);
    integer row_count = 0;         
    integer col_count = 0;        
    integer count = 0;         
    integer nbgh_row_count = 0;   

    // Always block for control signals
    always @(posedge clk) begin
        if (master_rst) begin
            sel <= 2'b00;
            load_sr <= 0;
            rst_m <= 0;
            op_en <= 0;
            global_rst <= 1;
            end_op <= 0;
        end else begin
            // Case 4: End of neighbourhood in the last row
            if (((col_count + 1) % POOL_SIZE != 0) && (row_count == POOL_SIZE - 1) && 
                (col_count == POOL_SIZE * count + (POOL_SIZE - 2)) && ce) begin
                op_en <= 1;
            end else begin
                op_en <= 0;
            end

            if (ce) begin
                // Case 5: End of last neighbourhood of the last row
                if (nbgh_row_count == INPUT_SIZE / POOL_SIZE) begin
                    end_op <= 1;
                end else begin
                    end_op <= 0;
                end

                // Reset the entire module when the last column and row are reached
                if (((col_count + 1) % POOL_SIZE != 0) && (col_count == INPUT_SIZE - 2) && 
                    (row_count == POOL_SIZE - 1)) begin
                    global_rst <= 1;
                end else begin
                    global_rst <= 0;
                end

                // Case 3: Reset max register at the end of the neighbourhood
                if ((((col_count + 1) % POOL_SIZE == 0) && (count != INPUT_SIZE / POOL_SIZE - 1) && 
                    (row_count != POOL_SIZE - 1)) || ((col_count == INPUT_SIZE - 1) && 
                    (row_count == POOL_SIZE - 1))) begin
                    rst_m <= 1;
                end else begin
                    rst_m <= 0;
                end

                // Selector logic
                if (((col_count + 1) % POOL_SIZE != 0) && (col_count == INPUT_SIZE - 2) && 
                    (row_count == POOL_SIZE - 1)) begin
                    sel <= 2'b10;
                end else if ((((col_count) % POOL_SIZE == 0) && (count == INPUT_SIZE / POOL_SIZE - 1) && 
                            (row_count != POOL_SIZE - 1)) || 
                           (((col_count) % POOL_SIZE == 0) && (count != INPUT_SIZE / POOL_SIZE - 1) && 
                            (row_count == POOL_SIZE - 1))) begin
                    sel <= 2'b01;
                end else begin
                    sel <= 2'b00;
                end

                // Case 2: Load the shift register
                if ((((col_count + 1) % POOL_SIZE == 0) && (count == INPUT_SIZE / POOL_SIZE - 1)) || 
                    (((col_count + 1) % POOL_SIZE == 0) && (count != INPUT_SIZE / POOL_SIZE - 1))) begin
                    load_sr <= 1;
                end else begin
                    load_sr <= 0;
                end
            end
        end
    end

    // Always block for counters
    always @(posedge clk) begin
        if (master_rst) begin
            row_count <= 0;
            col_count <= 32'hffffffff;
            count <= 32'hffffffff;
            nbgh_row_count <= 0;
        end else if (ce) begin
            if (global_rst) begin
                row_count <= 0;
                col_count <= 0;
                count <= 0;
                nbgh_row_count <= nbgh_row_count + 1;
            end else begin
                // Update column, row, and neighbourhood counters
                if (((col_count + 1) % POOL_SIZE == 0) && (count == INPUT_SIZE / POOL_SIZE - 1) && 
                    (row_count != POOL_SIZE - 1)) begin
                    col_count <= 0;
                    row_count <= row_count + 1;
                    count <= 0;
                end else begin
                    col_count <= col_count + 1;
                    if (((col_count + 1) % POOL_SIZE == 0) && (count != INPUT_SIZE / POOL_SIZE - 1)) begin
                        count <= count + 1;
                    end
                end
            end
        end
    end
endmodule

source/pooler.v
`timescale 1ns / 1ps

module pooler #(
    parameter INPUT_SIZE = 9'h004,              // Input matrix size (rows/columns)
    parameter POOL_SIZE = 9'h002,               // Pooling window size
    parameter DATA_WIDTH = 16,                  // Data width for inputs/outputs
    parameter POOL_TYPE = 1                     // Pooling type: 0 -> Average, 1 -> Max
)(
    input clk,                                  // Clock signal
    input ce,                                   // Clock enable signal
    input master_rst,                           // Master reset
    input [DATA_WIDTH-1:0] data_in,            // Input data
    output [DATA_WIDTH-1:0] data_out,          // Output data
    output valid_op,                            // Signal indicating valid output
    output end_op                               // Signal indicating all outputs are completed
);

    // Internal control signals
    wire rst_m;                               
    wire load_sr;                              
    wire global_rst;                            
    wire [1:0] sel;                            
    // Internal data signals
    wire [DATA_WIDTH-1:0] comp_op;              
    wire [DATA_WIDTH-1:0] sr_op;                
    wire [DATA_WIDTH-1:0] max_reg_op;            
    wire [DATA_WIDTH-1:0] div_op;               
    wire [DATA_WIDTH-1:0] mux_out;             

    // Instantiate the control logic to generate control signals
    control_logic2 #(.INPUT_SIZE(INPUT_SIZE), .POOL_SIZE(POOL_SIZE)) control_logic_inst (
        .clk(clk),
        .master_rst(master_rst),
        .ce(ce),
        .sel(sel),
        .rst_m(rst_m),
        .op_en(valid_op),
        .load_sr(load_sr),
        .global_rst(global_rst),
        .end_op(end_op)
    );

    // Comparator to compare the current input and the selected previous value
    comparator2 #(
        .DATA_WIDTH(DATA_WIDTH),
        .POOL_TYPE(POOL_TYPE)
    ) comparator_inst (
        .ce(ce),
        .in1(data_in),
        .in2(mux_out),
        .comp_op(comp_op)
    );

    // Max register to store the maximum value (or intermediate values)
    max_reg #(
        .DATA_WIDTH(DATA_WIDTH)
    ) max_reg_inst (
        .clk(clk),
        .ce(ce),
        .data_in(comp_op),
        .rst_m(rst_m),
        .master_rst(master_rst),
        .reg_op(max_reg_op)
    );

    // Shift register for storing intermediate values for row-wise pooling
    shift_register #(
        .DATA_WIDTH(DATA_WIDTH),
        .size(INPUT_SIZE / POOL_SIZE)
    ) shift_register_inst (
        .clk(clk),
        .ce(load_sr),
        .rst(global_rst && master_rst),
        .data_in(comp_op),
        .data_out(sr_op)
    );

    // Multiplexer to select between shift register output and max register output
    input_mux #(
        .DATA_WIDTH(DATA_WIDTH)
    ) mux_inst (
        .in1(sr_op),           
        .in2(max_reg_op),     
        .sel(sel),             
        .op(mux_out)      
    );

    assign div_op = max_reg_op / (POOL_SIZE * POOL_SIZE);
    // Output data selection: max value for max pooling or scaled sum for average pooling
    assign data_out = POOL_TYPE ? max_reg_op : div_op;

endmodule

verification/pooler/pooler_tb.v
`timescale 1ns/1ps
module pooler_tb;

    // Parameters
    parameter INPUT_SIZE = 26;              // Input matrix size (rows/columns)
    parameter POOL_SIZE = 2;                // Pooling window size
    parameter DATA_WIDTH = 8;               // Data width for inputs/outputs
    parameter POOL_TYPE = 1;                // Pooling type: 0 -> Average, 1 -> Max

    // Clock and reset signals
    reg clk;
    reg ce;
    reg master_rst;

    // Input and output signals
    reg [DATA_WIDTH-1:0] data_in;
    wire [DATA_WIDTH-1:0] data_out;
    wire valid_op;
    wire end_op;

    // Memory for input and expected output data
    reg [DATA_WIDTH-1:0] input_data [0:INPUT_SIZE*INPUT_SIZE-1];          // Assuming INPUT_SIZE x INPUT_SIZE matrix for input
    reg [DATA_WIDTH-1:0] pooling_out_data [0:(INPUT_SIZE/POOL_SIZE)*(INPUT_SIZE/POOL_SIZE)-1]; // Expected output data
    integer pass_count = 0;
    integer fail_count = 0;
    integer i;

    // Instantiate the pooler module
    pooler #(
        .INPUT_SIZE(INPUT_SIZE),
        .POOL_SIZE(POOL_SIZE),
        .DATA_WIDTH(DATA_WIDTH),
        .POOL_TYPE(POOL_TYPE)
    ) uut (
        .clk(clk),
        .ce(ce),
        .master_rst(master_rst),
        .data_in(data_in),
        .data_out(data_out),
        .valid_op(valid_op),
        .end_op(end_op)
    );

    // Clock generation
    initial clk = 0;
    always #5 clk = ~clk; // 10 ns clock period

    // Testbench initialization
    initial begin
        // Initialize signals
        ce = 0;
        master_rst = 1;
        data_in = 0;

        // Read input data from file
        $readmemb("../../python/relu_output.txt", input_data);
        // Read expected pooling output data from file
        $readmemb("../../python/pooling_output.txt", pooling_out_data);

        // Wait for reset deassertion
        #20;
        master_rst = 0;
        ce = 1;

        // Feed input data to the module
        for (i = 0; i < INPUT_SIZE * INPUT_SIZE; i = i + 1) begin
            data_in = input_data[i];
            #10; // Wait for one clock cycle
        end

        // Stop clock enable to finish the operation
        ce = 0;
        #200;

        // Report final test results
        $display("\nSimulation Results:");
        if (fail_count == 0) begin
            $display("All tests passed (%d/%d outputs)", pass_count, pass_count);
        end else begin
            $display("Test failed for %d outputs (%d/%d passed)", fail_count, pass_count, pass_count + fail_count);
        end

        // End simulation
        $finish;
    end

    // Monitor and compare outputs
    always @(posedge clk) begin
        if (valid_op == 1 && end_op == 0) begin
            // Compare data_out with pooling_out_data
            if (pass_count < (INPUT_SIZE/POOL_SIZE) * (INPUT_SIZE/POOL_SIZE)) begin
                if (data_out == pooling_out_data[pass_count]) begin
                    $display("Test Passed for output %d: %b", pass_count, data_out);
                    pass_count = pass_count + 1;
                end else begin
                    $display("Test Failed for output %d: expected %b, got %b", pass_count, pooling_out_data[pass_count], data_out);
                    fail_count = fail_count + 1;
                    pass_count = pass_count + 1;
                end
            end
        end
    end

    // Dump waveform for GTKWave
    initial begin
        $dumpfile("wave.vcd");
        $dumpvars(0, pooler_tb);
    end

endmodule

verification/pooler/wave.vcd
$date
	Sat Dec 28 13:46:08 2024
$end
$version
	Icarus Verilog
$end
$timescale
	1ps
$end
$scope module pooler_tb $end
$var wire 1 ! valid_op $end
$var wire 1 " end_op $end
$var wire 8 # data_out [7:0] $end
$var parameter 32 $ DATA_WIDTH $end
$var parameter 32 % INPUT_SIZE $end
$var parameter 32 & POOL_SIZE $end
$var parameter 32 ' POOL_TYPE $end
$var reg 1 ( ce $end
$var reg 1 ) clk $end
$var reg 8 * data_in [7:0] $end
$var reg 1 + master_rst $end
$var integer 32 , fail_count [31:0] $end
$var integer 32 - i [31:0] $end
$var integer 32 . pass_count [31:0] $end
$scope module uut $end
$var wire 1 ( ce $end
$var wire 1 ) clk $end
$var wire 8 / data_in [7:0] $end
$var wire 8 0 data_out [7:0] $end
$var wire 1 + master_rst $end
$var wire 8 1 sr_op [7:0] $end
$var wire 1 ! valid_op $end
$var wire 2 2 sel [1:0] $end
$var wire 1 3 rst_m $end
$var wire 8 4 mux_out [7:0] $end
$var wire 8 5 max_reg_op [7:0] $end
$var wire 1 6 load_sr $end
$var wire 1 7 global_rst $end
$var wire 1 " end_op $end
$var wire 8 8 div_op [7:0] $end
$var wire 8 9 comp_op [7:0] $end
$var parameter 32 : DATA_WIDTH $end
$var parameter 32 ; INPUT_SIZE $end
$var parameter 32 < POOL_SIZE $end
$var parameter 32 = POOL_TYPE $end
$scope module comparator_inst $end
$var wire 1 ( ce $end
$var wire 8 > in1 [7:0] $end
$var wire 8 ? in2 [7:0] $end
$var wire 8 @ comp_op [7:0] $end
$var parameter 32 A DATA_WIDTH $end
$var parameter 32 B POOL_TYPE $end
$var reg 8 C temp [7:0] $end
$upscope $end
$scope module control_logic_inst $end
$var wire 1 ( ce $end
$var wire 1 ) clk $end
$var wire 1 + master_rst $end
$var parameter 32 D INPUT_SIZE $end
$var parameter 32 E POOL_SIZE $end
$var reg 1 " end_op $end
$var reg 1 7 global_rst $end
$var reg 1 6 load_sr $end
$var reg 1 ! op_en $end
$var reg 1 3 rst_m $end
$var reg 2 F sel [1:0] $end
$var integer 32 G col_count [31:0] $end
$var integer 32 H count [31:0] $end
$var integer 32 I nbgh_row_count [31:0] $end
$var integer 32 J row_count [31:0] $end
$upscope $end
$scope module max_reg_inst $end
$var wire 1 ( ce $end
$var wire 1 ) clk $end
$var wire 8 K data_in [7:0] $end
$var wire 1 + master_rst $end
$var wire 1 3 rst_m $end
$var parameter 32 L DATA_WIDTH $end
$var reg 8 M reg_op [7:0] $end
$upscope $end
$scope module mux_inst $end
$var wire 8 N in1 [7:0] $end
$var wire 8 O in2 [7:0] $end
$var wire 2 P sel [1:0] $end
$var wire 8 Q op [7:0] $end
$var parameter 32 R DATA_WIDTH $end
$upscope $end
$scope module shift_register_inst $end
$var wire 1 6 ce $end
$var wire 1 ) clk $end
$var wire 8 S data_in [7:0] $end
$var wire 8 T data_out [7:0] $end
$var wire 1 U rst $end
$var parameter 32 V DATA_WIDTH $end
$var parameter 32 W size $end
$scope begin genblk1[0] $end
$var parameter 2 X l $end
$upscope $end
$scope begin genblk1[1] $end
$var parameter 2 Y l $end
$upscope $end
$scope begin genblk1[2] $end
$var parameter 3 Z l $end
$upscope $end
$scope begin genblk1[3] $end
$var parameter 3 [ l $end
$upscope $end
$scope begin genblk1[4] $end
$var parameter 4 \ l $end
$upscope $end
$scope begin genblk1[5] $end
$var parameter 4 ] l $end
$upscope $end
$scope begin genblk1[6] $end
$var parameter 4 ^ l $end
$upscope $end
$scope begin genblk1[7] $end
$var parameter 4 _ l $end
$upscope $end
$scope begin genblk1[8] $end
$var parameter 5 ` l $end
$upscope $end
$scope begin genblk1[9] $end
$var parameter 5 a l $end
$upscope $end
$scope begin genblk1[10] $end
$var parameter 5 b l $end
$upscope $end
$scope begin genblk1[11] $end
$var parameter 5 c l $end
$upscope $end
$scope begin genblk1[12] $end
$var parameter 5 d l $end
$upscope $end
$upscope $end
$upscope $end
$upscope $end
$enddefinitions $end
$comment Show the parameter values. $end
$dumpall
b1100 d
b1011 c
b1010 b
b1001 a
b1000 `
b111 _
b110 ^
b101 ]
b100 \
b11 [
b10 Z
b1 Y
b0 X
b1101 W
b1000 V
b1000 R
b1000 L
b10 E
b11010 D
b1 B
b1000 A
b1 =
b10 <
b11010 ;
b1000 :
b1 '
b10 &
b11010 %
b1000 $
$end
#0
$dumpvars
xU
bx T
b0 S
bx Q
bx P
bx O
bx N
bx M
b0 K
b0 J
b0 I
b0 H
b0 G
bx F
bx C
b0 @
bx ?
b0 >
b0 9
bx 8
x7
x6
bx 5
bx 4
x3
bx 2
bx 1
bx 0
b0 /
b0 .
bx -
b0 ,
1+
b0 *
0)
0(
bx #
x"
x!
$end
#5000
b0 C
1U
b0 4
b0 ?
b0 Q
b0 8
0"
17
0!
03
06
b0 2
b0 F
b0 P
b11111111111111111111111111111111 H
b11111111111111111111111111111111 G
b0 #
b0 0
b0 5
b0 M
b0 O
1)
#10000
0)
#15000
b0 1
b0 N
b0 T
1)
#20000
b10100 9
b10100 @
b10100 K
b10100 S
b10100 C
0U
0)
b10100 *
b10100 /
b10100 >
b0 -
1(
0+
#25000
b10100 4
b10100 ?
b10100 Q
b101 8
16
13
07
b1 I
b0 H
b0 G
b10100 #
b10100 0
b10100 5
b10100 M
b10100 O
1)
#30000
0)
b0 *
b0 /
b0 >
b1 -
#35000
b0 9
b0 @
b0 K
b0 S
b0 C
b0 4
b0 ?
b0 Q
b0 8
b0 #
b0 0
b0 5
b0 M
b0 O
b1 G
06
03
1)
#40000
b111 9
b111 @
b111 K
b111 S
b111 C
0)
b111 *
b111 /
b111 >
b10 -
#45000
b111 4
b111 ?
b111 Q
b1 8
16
13
b1 H
b10 G
b111 #
b111 0
b111 5
b111 M
b111 O
1)
#50000
b10100 9
b10100 @
b10100 K
b10100 S
b10100 C
0)
b10100 *
b10100 /
b10100 >
b11 -
#55000
b0 4
b0 ?
b0 Q
b0 8
b0 #
b0 0
b0 5
b0 M
b0 O
b11 G
06
03
1)
#60000
b10010 9
b10010 @
b10010 K
b10010 S
b10010 C
0)
b10010 *
b10010 /
b10010 >
b100 -
#65000
b10010 4
b10010 ?
b10010 Q
b100 8
16
13
b10 H
b100 G
b10010 #
b10010 0
b10010 5
b10010 M
b10010 O
1)
#70000
0)
b1010 *
b1010 /
b1010 >
b101 -
#75000
b1010 9
b1010 @
b1010 K
b1010 S
b1010 C
b0 4
b0 ?
b0 Q
b0 8
b0 #
b0 0
b0 5
b0 M
b0 O
b101 G
06
03
1)
#80000
b0 9
b0 @
b0 K
b0 S
b0 C
0)
b0 *
b0 /
b0 >
b110 -
#85000
16
13
b11 H
b110 G
1)
#90000
0)
b111 -
#95000
b111 G
06
03
1)
#100000
b1100 9
b1100 @
b1100 K
b1100 S
b1100 C
0)
b1100 *
b1100 /
b1100 >
b1000 -
#105000
b1100 4
b1100 ?
b1100 Q
b11 8
16
13
b100 H
b1000 G
b1100 #
b1100 0
b1100 5
b1100 M
b1100 O
1)
#110000
b10010 9
b10010 @
b10010 K
b10010 S
b10010 C
0)
b10010 *
b10010 /
b10010 >
b1001 -
#115000
b0 4
b0 ?
b0 Q
b0 8
b0 #
b0 0
b0 5
b0 M
b0 O
b1001 G
06
03
1)
#120000
b1110 9
b1110 @
b1110 K
b1110 S
b1110 C
0)
b1110 *
b1110 /
b1110 >
b1010 -
#125000
b1110 4
b1110 ?
b1110 Q
b11 8
16
13
b101 H
b1010 G
b1110 #
b1110 0
b1110 5
b1110 M
b1110 O
1)
#130000
b10110 9
b10110 @
b10110 K
b10110 S
b10110 C
0)
b10110 *
b10110 /
b10110 >
b1011 -
#135000
b0 4
b0 ?
b0 Q
b0 8
b0 #
b0 0
b0 5
b0 M
b0 O
b1011 G
06
03
1)
#140000
b1100 9
b1100 @
b1100 K
b1100 S
b1100 C
0)
b1100 *
b1100 /
b1100 >
b1100 -
#145000
b1100 4
b1100 ?
b1100 Q
b11 8
16
13
b110 H
b1100 G
b1100 #
b1100 0
b1100 5
b1100 M
b1100 O
1)
#150000
0)
b0 *
b0 /
b0 >
b1101 -
#155000
b0 9
b0 @
b0 K
b0 S
b0 C
b0 4
b0 ?
b0 Q
b0 8
b0 #
b0 0
b0 5
b0 M
b0 O
b1101 G
06
03
1)
#160000
b10 9
b10 @
b10 K
b10 S
b10 C
0)
b10 *
b10 /
b10 >
b1110 -
#165000
b10 4
b10 ?
b10 Q
16
13
b111 H
b1110 G
b10 #
b10 0
b10 5
b10 M
b10 O
1)
#170000
0)
b0 *
b0 /
b0 >
b1111 -
#175000
b0 9
b0 @
b0 K
b0 S
b0 C
b0 4
b0 ?
b0 Q
b0 #
b0 0
b0 5
b0 M
b0 O
b1111 G
06
03
1)
#180000
0)
b10000 -
#185000
16
13
b1000 H
b10000 G
1)
#190000
0)
b10001 -
#195000
b10001 G
06
03
1)
#200000
b11 9
b11 @
b11 K
b11 S
b11 C
0)
b11 *
b11 /
b11 >
b10010 -
#205000
b11 4
b11 ?
b11 Q
16
13
b1001 H
b10010 G
b11 #
b11 0
b11 5
b11 M
b11 O
1)
#210000
b101 9
b101 @
b101 K
b101 S
b101 C
0)
b101 *
b101 /
b101 >
b10011 -
#215000
b0 4
b0 ?
b0 Q
b0 #
b0 0
b0 5
b0 M
b0 O
b10011 G
06
03
1)
#220000
b1110 9
b1110 @
b1110 K
b1110 S
b1110 C
0)
b1110 *
b1110 /
b1110 >
b10100 -
#225000
b1110 4
b1110 ?
b1110 Q
b11 8
16
13
b1010 H
b10100 G
b1110 #
b1110 0
b1110 5
b1110 M
b1110 O
1)
#230000
b1111 9
b1111 @
b1111 K
b1111 S
b1111 C
0)
b1111 *
b1111 /
b1111 >
b10101 -
#235000
b0 4
b0 ?
b0 Q
b0 8
b0 #
b0 0
b0 5
b0 M
b0 O
b10101 G
06
03
1)
#240000
b111 9
b111 @
b111 K
b111 S
b111 C
0)
b111 *
b111 /
b111 >
b10110 -
#245000
b111 4
b111 ?
b111 Q
b1 8
16
13
b1011 H
b10110 G
b111 #
b111 0
b111 5
b111 M
b111 O
1)
#250000
0)
b10111 -
#255000
b0 4
b0 ?
b0 Q
b0 8
b0 #
b0 0
b0 5
b0 M
b0 O
b10111 G
06
03
1)
#260000
b10000 9
b10000 @
b10000 K
b10000 S
b10000 C
0)
b10000 *
b10000 /
b10000 >
b11000 -
#265000
b10000 4
b10000 ?
b10000 Q
b100 8
16
13
b1100 H
b11000 G
b10000 #
b10000 0
b10000 5
b10000 M
b10000 O
1)
#270000
b10010 9
b10010 @
b10010 K
b10010 S
b10010 C
0)
b10010 *
b10010 /
b10010 >
b11001 -
#275000
b10100 9
b10100 @
b10100 K
b10100 S
b10100 C
b0 8
b10100 4
b10100 ?
b10100 Q
b10100 1
b10100 N
b10100 T
b0 #
b0 0
b0 5
b0 M
b0 O
b11001 G
06
b1 2
b1 F
b1 P
03
1)
#280000
0)
b1010 *
b1010 /
b1010 >
b11010 -
#285000
b101 8
16
b0 2
b0 F
b0 P
b0 H
b1 J
b0 G
b10100 #
b10100 0
b10100 5
b10100 M
b10100 O
1)
#290000
0)
b0 *
b0 /
b0 >
b11011 -
#295000
b1 G
06
b1 2
b1 F
b1 P
1!
1)
#300000
0)
b111 *
b111 /
b111 >
b11100 -
#305000
16
b0 2
b0 F
b0 P
0!
b1 H
b10 G
b1 .
1)
#310000
0)
b0 *
b0 /
b0 >
b11101 -
#315000
b10010 9
b10010 @
b10010 K
b10010 S
b10010 C
b10010 4
b10010 ?
b10010 Q
b10010 1
b10010 N
b10010 T
b11 G
06
b1 2
b1 F
b1 P
1!
1)
#320000
0)
b11110 -
#325000
b100 8
16
b0 2
b0 F
b0 P
0!
b10 H
b100 G
b10010 #
b10010 0
b10010 5
b10010 M
b10010 O
b10 .
1)
#330000
0)
b11111 -
#335000
b0 9
b0 @
b0 K
b0 S
b0 C
b0 4
b0 ?
b0 Q
b0 1
b0 N
b0 T
b101 G
06
b1 2
b1 F
b1 P
1!
1)
#340000
0)
b100000 -
#345000
b0 8
16
b0 2
b0 F
b0 P
0!
b11 H
b110 G
b0 #
b0 0
b0 5
b0 M
b0 O
b11 .
1)
#350000
b1 9
b1 @
b1 K
b1 S
b1 C
0)
b1 *
b1 /
b1 >
b100001 -
#355000
b10010 9
b10010 @
b10010 K
b10010 S
b10010 C
b10010 4
b10010 ?
b10010 Q
b10010 1
b10010 N
b10010 T
b1 #
b1 0
b1 5
b1 M
b1 O
b111 G
06
b1 2
b1 F
b1 P
1!
1)
#360000
0)
b110 *
b110 /
b110 >
b100010 -
#365000
b100 8
16
b0 2
b0 F
b0 P
0!
b100 H
b1000 G
b10010 #
b10010 0
b10010 5
b10010 M
b10010 O
b100 .
1)
#370000
0)
b0 *
b0 /
b0 >
b100011 -
#375000
b10110 9
b10110 @
b10110 K
b10110 S
b10110 C
b10110 4
b10110 ?
b10110 Q
b10110 1
b10110 N
b10110 T
b1001 G
06
b1 2
b1 F
b1 P
1!
1)
#380000
0)
b11 *
b11 /
b11 >
b100100 -
#385000
b101 8
16
b0 2
b0 F
b0 P
0!
b101 H
b1010 G
b10110 #
b10110 0
b10110 5
b10110 M
b10110 O
b101 .
1)
#390000
0)
b10101 *
b10101 /
b10101 >
b100101 -
#395000
b10101 9
b10101 @
b10101 K
b10101 S
b10101 C
b1100 4
b1100 ?
b1100 Q
b1100 1
b1100 N
b1100 T
b1011 G
06
b1 2
b1 F
b1 P
1!
1)
#400000
b1111 9
b1111 @
b1111 K
b1111 S
b1111 C
0)
b1111 *
b1111 /
b1111 >
b100110 -
#405000
b1111 4
b1111 ?
b1111 Q
b11 8
16
b0 2
b0 F
b0 P
0!
b110 H
b1100 G
b1111 #
b1111 0
b1111 5
b1111 M
b1111 O
b110 .
1)
#410000
b10001 9
b10001 @
b10001 K
b10001 S
b10001 C
0)
b10001 *
b10001 /
b10001 >
b100111 -
#415000
b100 8
b10 4
b10 ?
b10 Q
b10 1
b10 N
b10 T
b10001 #
b10001 0
b10001 5
b10001 M
b10001 O
b1101 G
06
b1 2
b1 F
b1 P
1!
1)
#420000
b10000 9
b10000 @
b10000 K
b10000 S
b10000 C
0)
b10000 *
b10000 /
b10000 >
b101000 -
#425000
b10000 4
b10000 ?
b10000 Q
16
b0 2
b0 F
b0 P
0!
b111 H
b1110 G
b10000 #
b10000 0
b10000 5
b10000 M
b10000 O
b111 .
1)
#430000
0)
b1010 *
b1010 /
b1010 >
b101001 -
#435000
b1010 9
b1010 @
b1010 K
b1010 S
b1010 C
b0 4
b0 ?
b0 Q
b0 1
b0 N
b0 T
b1111 G
06
b1 2
b1 F
b1 P
1!
1)
#440000
b1011 9
b1011 @
b1011 K
b1011 S
b1011 C
0)
b1011 *
b1011 /
b1011 >
b101010 -
#445000
b1011 4
b1011 ?
b1011 Q
b10 8
16
b0 2
b0 F
b0 P
0!
b1000 H
b10000 G
b1011 #
b1011 0
b1011 5
b1011 M
b1011 O
b1000 .
1)
#450000
0)
b0 *
b0 /
b0 >
b101011 -
#455000
b101 9
b101 @
b101 K
b101 S
b101 C
b101 4
b101 ?
b101 Q
b101 1
b101 N
b101 T
b10001 G
06
b1 2
b1 F
b1 P
1!
1)
#460000
0)
b101100 -
#465000
b1 8
16
b0 2
b0 F
b0 P
0!
b1001 H
b10010 G
b101 #
b101 0
b101 5
b101 M
b101 O
b1001 .
1)
#470000
0)
b101101 -
#475000
b1111 9
b1111 @
b1111 K
b1111 S
b1111 C
b1111 4
b1111 ?
b1111 Q
b1111 1
b1111 N
b1111 T
b10011 G
06
b1 2
b1 F
b1 P
1!
1)
#480000
b10010 9
b10010 @
b10010 K
b10010 S
b10010 C
0)
b10010 *
b10010 /
b10010 >
b101110 -
#485000
b10010 4
b10010 ?
b10010 Q
b100 8
16
b0 2
b0 F
b0 P
0!
b1010 H
b10100 G
b10010 #
b10010 0
b10010 5
b10010 M
b10010 O
b1010 .
1)
#490000
0)
b0 *
b0 /
b0 >
b101111 -
#495000
b111 9
b111 @
b111 K
b111 S
b111 C
b111 4
b111 ?
b111 Q
b111 1
b111 N
b111 T
b10101 G
06
b1 2
b1 F
b1 P
1!
1)
#500000
b1110 9
b1110 @
b1110 K
b1110 S
b1110 C
0)
b1110 *
b1110 /
b1110 >
b110000 -
#505000
b1110 4
b1110 ?
b1110 Q
b11 8
16
b0 2
b0 F
b0 P
0!
b1011 H
b10110 G
b1110 #
b1110 0
b1110 5
b1110 M
b1110 O
b1011 .
1)
#510000
0)
b0 *
b0 /
b0 >
b110001 -
#515000
b10010 9
b10010 @
b10010 K
b10010 S
b10010 C
b10010 4
b10010 ?
b10010 Q
b10010 1
b10010 N
b10010 T
b10111 G
06
b1 2
b1 F
b1 P
1!
1)
#520000
0)
b1010 *
b1010 /
b1010 >
b110010 -
#525000
b100 8
16
b0 2
b0 F
b0 P
0!
b1100 H
b11000 G
b10010 #
b10010 0
b10010 5
b10010 M
b10010 O
b1100 .
1)
#530000
b11001 9
b11001 @
b11001 K
b11001 S
b11001 C
0)
b11001 *
b11001 /
b11001 >
b110011 -
#535000
b0 4
b0 ?
b0 Q
b110 8
b10100 1
b10100 N
b10100 T
b11001 #
b11001 0
b11001 5
b11001 M
b11001 O
b11001 G
06
b10 2
b10 F
b10 P
17
1!
1)
#540000
b11010 9
b11010 @
b11010 K
b11010 S
b11010 C
0)
b11010 *
b11010 /
b11010 >
b110100 -
#545000
b11010 4
b11010 ?
b11010 Q
16
b0 2
b0 F
b0 P
13
07
0!
b10 I
b0 H
b0 G
b0 J
b11010 #
b11010 0
b11010 5
b11010 M
b11010 O
b1101 .
1)
#550000
0)
b0 *
b0 /
b0 >
b110101 -
#555000
b0 9
b0 @
b0 K
b0 S
b0 C
b0 4
b0 ?
b0 Q
b0 8
b0 #
b0 0
b0 5
b0 M
b0 O
b1 G
06
03
1)
#560000
0)
b110110 -
#565000
16
13
b1 H
b10 G
1)
#570000
b101 9
b101 @
b101 K
b101 S
b101 C
0)
b101 *
b101 /
b101 >
b110111 -
#575000
b10010 1
b10010 N
b10010 T
b11 G
06
03
1)
#580000
b1101 9
b1101 @
b1101 K
b1101 S
b1101 C
0)
b1101 *
b1101 /
b1101 >
b111000 -
#585000
b1101 4
b1101 ?
b1101 Q
b11 8
16
13
b10 H
b100 G
b1101 #
b1101 0
b1101 5
b1101 M
b1101 O
1)
#590000
0)
b1001 *
b1001 /
b1001 >
b111001 -
#595000
b1001 9
b1001 @
b1001 K
b1001 S
b1001 C
b0 4
b0 ?
b0 Q
b0 8
b1 1
b1 N
b1 T
b0 #
b0 0
b0 5
b0 M
b0 O
b101 G
06
03
1)
#600000
b0 9
b0 @
b0 K
b0 S
b0 C
0)
b0 *
b0 /
b0 >
b111010 -
