source/defines.v
// Parameters
`define dataWidth = 8;
`define W = 58;
`define K = 3;
`define P = 2;
`define s = 1;
`define actype = 1'b1;  // 0 => tanh, 1 => relu

source/input_mux.v
`timescale 1ns / 1ps

module input_mux #(
    parameter dataWidth = 8
)(
    input [dataWidth-1:0] in1,
    input [dataWidth-1:0] in2,
    input [1:0] sel,
    output [dataWidth-1:0] op
    );
    assign op = (sel == 2'b01) ? in1 : ((sel == 2'b00) ? in2: 0);
endmodule

source/shift_register.v
`timescale 1ns/1ps
`include "defines.v"

module shift_register #(
    parameter dataWidth = 16,
    parameter size = 3
)(
    input clk, ce, rst,
    input [dataWidth-1:0] data_in,
    output [dataWidth-1:0] data_out
);
    reg [dataWidth-1:0] tmp[size-1:0];
    
    generate
        genvar l;
        for (l = 0; l < size; l = l + 1) begin
            always @(posedge clk) begin
                if (rst) begin
                    tmp[l] <= 'd0;
                end
                else if (ce) begin
                    if (l == 'd0) begin
                        tmp[l] <= data_in;  
                    end
                    else begin
                        tmp[l] <= tmp[l-1];
                    end
                end
            end
        end
    assign data_out = tmp[size-1];
    endgenerate
    
endmodule

source/max_reg.v
`timescale 1ns / 1ps
module max_reg #(parameter N = 16) (
    input clk,
    input ce,
    input [N-1:0] data_in,
    input rst_m,
    input master_rst,
    output reg [N-1:0] reg_op
    );

    always@(posedge clk) 
    begin
    	if(master_rst)
    		reg_op <= 0;
    	else 
        begin
            if(ce) 
            begin
		   	  if(rst_m) begin
		    	 reg_op <=0;
		      end
		      else begin
		    	 reg_op <= data_in;
			 end
		    end
		end
	end
endmodule

source/comparator2.v
`timescale 1ns / 1ps

module comparator2 #(
    parameter dataWidth = 16,
    parameter ptype = 1
    )(
    input ce,
    input [dataWidth-1:0] in1,
    input [dataWidth-1:0] in2,
    output [dataWidth-1:0] comp_op
    ); 
    reg [dataWidth-1:0] temp;
    assign comp_op = ce ? temp : 'd0;

    always@(*)
    begin
        if(ptype == 0)
        begin
            temp = in1 + in2;        
        end
        else begin
            temp = (in1 > in2) ? in1 : in2;
        end
    end
endmodule

source/control_logic2.v
`timescale 1ns / 1ps

module control_logic2 #(
    parameter M = 9'h004,   // Total number of rows in the input
    parameter P = 9'h002    // Pooling size (both width and height)
)(
    input clk,             
    input master_rst,       
    input ce,            
    output reg [1:0] sel, 
    output reg rst_m,     
    output reg op_en,      
    output reg load_sr,    
    output reg global_rst,  
    output reg end_op       
);
    integer row_count = 0;         
    integer col_count = 0;        
    integer count = 0;         
    integer nbgh_row_count = 0;   

    // Always block for control signals
    always @(posedge clk) begin
        if (master_rst) begin
            sel <= 2'b00;
            load_sr <= 0;
            rst_m <= 0;
            op_en <= 0;
            global_rst <= 1;
            end_op <= 0;
        end else begin
            // Case 4: End of neighbourhood in the last row
            if (((col_count + 1) % P != 0) && (row_count == P - 1) && 
                (col_count == P * count + (P - 2)) && ce) begin
                op_en <= 1;
            end else begin
                op_en <= 0;
            end

            if (ce) begin
                // Case 5: End of last neighbourhood of the last row
                if (nbgh_row_count == M / P) begin
                    end_op <= 1;
                end else begin
                    end_op <= 0;
                end

                // Reset the entire module when the last column and row are reached
                if (((col_count + 1) % P != 0) && (col_count == M - 2) && 
                    (row_count == P - 1)) begin
                    global_rst <= 1;
                end else begin
                    global_rst <= 0;
                end

                // Case 3: Reset max register at the end of the neighbourhood
                if ((((col_count + 1) % P == 0) && (count != M / P - 1) && 
                    (row_count != P - 1)) || ((col_count == M - 1) && 
                    (row_count == P - 1))) begin
                    rst_m <= 1;
                end else begin
                    rst_m <= 0;
                end

                // Selector logic
                if (((col_count + 1) % P != 0) && (col_count == M - 2) && 
                    (row_count == P - 1)) begin
                    sel <= 2'b10;
                end else if ((((col_count) % P == 0) && (count == M / P - 1) && 
                            (row_count != P - 1)) || 
                           (((col_count) % P == 0) && (count != M / P - 1) && 
                            (row_count == P - 1))) begin
                    sel <= 2'b01;
                end else begin
                    sel <= 2'b00;
                end

                // Case 2: Load the shift register
                if ((((col_count + 1) % P == 0) && (count == M / P - 1)) || 
                    (((col_count + 1) % P == 0) && (count != M / P - 1))) begin
                    load_sr <= 1;
                end else begin
                    load_sr <= 0;
                end
            end
        end
    end

    // Always block for counters
    always @(posedge clk) begin
        if (master_rst) begin
            row_count <= 0;
            col_count <= 32'hffffffff;
            count <= 32'hffffffff;
            nbgh_row_count <= 0;
        end else if (ce) begin
            if (global_rst) begin
                row_count <= 0;
                col_count <= 0;
                count <= 0;
                nbgh_row_count <= nbgh_row_count + 1;
            end else begin
                // Update column, row, and neighbourhood counters
                if (((col_count + 1) % P == 0) && (count == M / P - 1) && 
                    (row_count != P - 1)) begin
                    col_count <= 0;
                    row_count <= row_count + 1;
                    count <= 0;
                end else begin
                    col_count <= col_count + 1;
                    if (((col_count + 1) % P == 0) && (count != M / P - 1)) begin
                        count <= count + 1;
                    end
                end
            end
        end
    end
endmodule

source/pooler.v
`timescale 1ns / 1ps

module pooler #(
    parameter M = 9'h004,                       // Input matrix size (rows/columns)
    parameter P = 9'h002,                       // Pooling window size
    parameter dataWidth = 16,                   // Data width for inputs/outputs
    parameter ptype = 1                         // Pooling type: 0 -> Average, 1 -> Max
)(
    input clk,                                  // Clock signal
    input ce,                                   // Clock enable signal
    input master_rst,                           // Master reset
    input [dataWidth-1:0] data_in,              // Input data
    output [dataWidth-1:0] data_out,            // Output data
    output valid_op,                            // Signal indicating valid output
    output end_op                               // Signal indicating all outputs are completed
);

    // Internal control signals
    wire rst_m;                               
    wire load_sr;                              
    wire global_rst;                            
    wire [1:0] sel;                            
    // Internal data signals
    wire [dataWidth-1:0] comp_op;              
    wire [dataWidth-1:0] sr_op;                
    wire [dataWidth-1:0] max_reg_op;            
    wire [dataWidth-1:0] div_op;               
    wire [dataWidth-1:0] mux_out;             

    // Instantiate the control logic to generate control signals
    control_logic2 #(.M(M), .P(P)) control_logic_inst (
        .clk(clk),
        .master_rst(master_rst),
        .ce(ce),
        .sel(sel),
        .rst_m(rst_m),
        .op_en(valid_op),
        .load_sr(load_sr),
        .global_rst(global_rst),
        .end_op(end_op)
    );

    // Comparator to compare the current input and the selected previous value
    comparator2 #(
        .dataWidth(dataWidth),
        .ptype(ptype)
    ) comparator_inst (
        .ce(ce),
        .in1(data_in),
        .in2(mux_out),
        .comp_op(comp_op)
    );

    // Max register to store the maximum value (or intermediate values)
    max_reg #(
        .N(dataWidth)
    ) max_reg_inst (
        .clk(clk),
        .ce(ce),
        .data_in(comp_op),
        .rst_m(rst_m),
        .master_rst(master_rst),
        .reg_op(max_reg_op)
    );

    // Shift register for storing intermediate values for row-wise pooling
    shift_register #(
        .dataWidth(dataWidth),
        .size(M / P)
    ) shift_register_inst (
        .clk(clk),
        .ce(load_sr),
        .rst(global_rst && master_rst),
        .data_in(comp_op),
        .data_out(sr_op)
    );

    // Multiplexer to select between shift register output and max register output
    input_mux #(
        .dataWidth(dataWidth)
    ) mux_inst (
        .in1(sr_op),           
        .in2(max_reg_op),     
        .sel(sel),             
        .op(mux_out)      
    );

    assign div_op = max_reg_op / (P * P);
    // Output data selection: max value for max pooling or scaled sum for average pooling
    assign data_out = ptype ? max_reg_op : div_op;

endmodule

verification/pooler/pooler_tb.v
`timescale 1ns/1ps
`include "defines.v"
module pooler_tb;

    // Parameters
    parameter M = 28;                  // Input matrix size (rows/columns)
    parameter P = 2;                  // Pooling window size
    parameter dataWidth = 8;              // Data width for inputs/outputs
    parameter ptype = 1;                   // Pooling type: 0 -> Average, 1 -> Max

    // Clock and reset signals
    reg clk;
    reg ce;
    reg master_rst;

    // Input and output signals
    reg [dataWidth-1:0] data_in;
    wire [dataWidth-1:0] data_out;
    wire valid_op;
    wire end_op;

    // Memory for input and expected output data
    reg [dataWidth-1:0] input_data [0:M*M-1];          // Assuming M x M matrix for input
    reg [dataWidth-1:0] pooling_out_data [0:(M/P)*(M/P)-1]; // Expected output data
    integer pass_count = 0;
    integer fail_count = 0;
    integer i;

    // Instantiate the pooler module
    pooler #(
        .M(M),
        .P(P),
        .dataWidth(dataWidth),
        .ptype(ptype)
    ) uut (
        .clk(clk),
        .ce(ce),
        .master_rst(master_rst),
        .data_in(data_in),
        .data_out(data_out),
        .valid_op(valid_op),
        .end_op(end_op)
    );

    // Clock generation
    initial clk = 0;
    always #5 clk = ~clk; // 10 ns clock period

    // Testbench initialization
    initial begin
        // Initialize signals
        ce = 0;
        master_rst = 1;
        data_in = 0;

        // Read input data from file
        $readmemb("../../python/relu_output.txt", input_data);
        // Read expected pooling output data from file
        $readmemb("../../python/pooling_output.txt", pooling_out_data);

        // Wait for reset deassertion
        #20;
        master_rst = 0;
        ce = 1;

        // Feed input data to the module
        for (i = 0; i < M * M; i = i + 1) begin
            data_in = input_data[i];
            #10; // Wait for one clock cycle
        end

        // Stop clock enable to finish the operation
        ce = 0;
        #200;

        // Report final test results
        $display("\nSimulation Results:");
        if (fail_count == 0) begin
            $display("All tests passed (%d/%d outputs)", pass_count, pass_count);
        end else begin
            $display("Test failed for %d outputs (%d/%d passed)", fail_count, pass_count, pass_count + fail_count);
        end

        // End simulation
        $finish;
    end

    // Monitor and compare outputs
    always @(posedge clk) begin
        if (valid_op == 1 && end_op == 0) begin
            // Compare data_out with pooling_out_data
            if (pass_count < (M/P) * (M/P)) begin
                if (data_out == pooling_out_data[pass_count]) begin
                    $display("Test Passed for output %d: %b", pass_count, data_out);
                    pass_count = pass_count + 1;
                end else begin
                    $display("Test Failed for output %d: expected %b, got %b", pass_count, pooling_out_data[pass_count], data_out);
                    fail_count = fail_count + 1;
                    pass_count = pass_count + 1;
                end
            end
        end
    end

    // Dump waveform for GTKWave
    initial begin
        $dumpfile("wave.vcd");
        $dumpvars(0, pooler_tb);
    end

endmodule

verification/pooler/wave.vcd
$date
	Sun Dec  8 07:55:09 2024
$end
$version
	Icarus Verilog
$end
$timescale
	1ps
$end
$scope module pooler_tb $end
$var wire 1 ! valid_op $end
$var wire 1 " end_op $end
$var wire 8 # data_out [7:0] $end
$var parameter 32 $ M $end
$var parameter 32 % P $end
$var parameter 32 & dataWidth $end
$var parameter 32 ' ptype $end
$var reg 1 ( ce $end
$var reg 1 ) clk $end
$var reg 8 * data_in [7:0] $end
$var reg 1 + master_rst $end
$var integer 32 , fail_count [31:0] $end
$var integer 32 - i [31:0] $end
$var integer 32 . pass_count [31:0] $end
$scope module uut $end
$var wire 1 ( ce $end
$var wire 1 ) clk $end
$var wire 8 / data_in [7:0] $end
$var wire 8 0 data_out [7:0] $end
$var wire 1 + master_rst $end
$var wire 8 1 sr_op [7:0] $end
$var wire 1 ! valid_op $end
$var wire 2 2 sel [1:0] $end
$var wire 1 3 rst_m $end
$var wire 8 4 mux_out [7:0] $end
$var wire 8 5 max_reg_op [7:0] $end
$var wire 1 6 load_sr $end
$var wire 1 7 global_rst $end
$var wire 1 " end_op $end
$var wire 8 8 div_op [7:0] $end
$var wire 8 9 comp_op [7:0] $end
$var parameter 32 : M $end
$var parameter 32 ; P $end
$var parameter 32 < dataWidth $end
$var parameter 32 = ptype $end
$scope module comparator_inst $end
$var wire 1 ( ce $end
$var wire 8 > in1 [7:0] $end
$var wire 8 ? in2 [7:0] $end
$var wire 8 @ comp_op [7:0] $end
$var parameter 32 A dataWidth $end
$var parameter 32 B ptype $end
$var reg 8 C temp [7:0] $end
$upscope $end
$scope module control_logic_inst $end
$var wire 1 ( ce $end
$var wire 1 ) clk $end
$var wire 1 + master_rst $end
$var parameter 32 D M $end
$var parameter 32 E P $end
$var reg 1 " end_op $end
$var reg 1 7 global_rst $end
$var reg 1 6 load_sr $end
$var reg 1 ! op_en $end
$var reg 1 3 rst_m $end
$var reg 2 F sel [1:0] $end
$var integer 32 G col_count [31:0] $end
$var integer 32 H count [31:0] $end
$var integer 32 I nbgh_row_count [31:0] $end
$var integer 32 J row_count [31:0] $end
$upscope $end
$scope module max_reg_inst $end
$var wire 1 ( ce $end
$var wire 1 ) clk $end
$var wire 8 K data_in [7:0] $end
$var wire 1 + master_rst $end
$var wire 1 3 rst_m $end
$var parameter 32 L N $end
$var reg 8 M reg_op [7:0] $end
$upscope $end
$scope module mux_inst $end
$var wire 8 N in1 [7:0] $end
$var wire 8 O in2 [7:0] $end
$var wire 2 P sel [1:0] $end
$var wire 8 Q op [7:0] $end
$var parameter 32 R dataWidth $end
$upscope $end
$scope module shift_register_inst $end
$var wire 1 6 ce $end
$var wire 1 ) clk $end
$var wire 8 S data_in [7:0] $end
$var wire 8 T data_out [7:0] $end
$var wire 1 U rst $end
$var parameter 32 V dataWidth $end
$var parameter 32 W size $end
$scope begin genblk1[0] $end
$var parameter 2 X l $end
$upscope $end
$scope begin genblk1[1] $end
$var parameter 2 Y l $end
$upscope $end
$scope begin genblk1[2] $end
$var parameter 3 Z l $end
$upscope $end
$scope begin genblk1[3] $end
$var parameter 3 [ l $end
$upscope $end
$scope begin genblk1[4] $end
$var parameter 4 \ l $end
$upscope $end
$scope begin genblk1[5] $end
$var parameter 4 ] l $end
$upscope $end
$scope begin genblk1[6] $end
$var parameter 4 ^ l $end
$upscope $end
$scope begin genblk1[7] $end
$var parameter 4 _ l $end
$upscope $end
$scope begin genblk1[8] $end
$var parameter 5 ` l $end
$upscope $end
$scope begin genblk1[9] $end
$var parameter 5 a l $end
$upscope $end
$scope begin genblk1[10] $end
$var parameter 5 b l $end
$upscope $end
$scope begin genblk1[11] $end
$var parameter 5 c l $end
$upscope $end
$scope begin genblk1[12] $end
$var parameter 5 d l $end
$upscope $end
$scope begin genblk1[13] $end
$var parameter 5 e l $end
$upscope $end
$upscope $end
$upscope $end
$upscope $end
$enddefinitions $end
$comment Show the parameter values. $end
$dumpall
b1101 e
b1100 d
b1011 c
b1010 b
b1001 a
b1000 `
b111 _
b110 ^
b101 ]
b100 \
b11 [
b10 Z
b1 Y
b0 X
b1110 W
b1000 V
b1000 R
b1000 L
b10 E
b11100 D
b1 B
b1000 A
b1 =
b1000 <
b10 ;
b11100 :
b1 '
b1000 &
b10 %
b11100 $
$end
#0
$dumpvars
xU
bx T
b0 S
bx Q
bx P
bx O
bx N
bx M
b0 K
b0 J
b0 I
b0 H
b0 G
bx F
bx C
b0 @
bx ?
b0 >
b0 9
bx 8
x7
x6
bx 5
bx 4
x3
bx 2
bx 1
bx 0
b0 /
b0 .
bx -
b0 ,
1+
b0 *
0)
0(
bx #
x"
x!
$end
#5000
b0 C
1U
b0 4
b0 ?
b0 Q
b0 8
0"
17
0!
03
06
b0 2
b0 F
b0 P
b11111111111111111111111111111111 H
b11111111111111111111111111111111 G
b0 #
b0 0
b0 5
b0 M
b0 O
1)
#10000
0)
#15000
b0 1
b0 N
b0 T
1)
#20000
b1011110 9
b1011110 @
b1011110 K
b1011110 S
b1011110 C
0U
0)
b1011110 *
b1011110 /
b1011110 >
b0 -
1(
0+
#25000
b1011110 4
b1011110 ?
b1011110 Q
b10111 8
16
13
07
b1 I
b0 H
b0 G
b1011110 #
b1011110 0
b1011110 5
b1011110 M
b1011110 O
1)
#30000
0)
b101001 *
b101001 /
b101001 >
b1 -
#35000
b101001 9
b101001 @
b101001 K
b101001 S
b101001 C
b0 4
b0 ?
b0 Q
b0 8
b0 #
b0 0
b0 5
b0 M
b0 O
b1 G
06
03
1)
#40000
b0 9
b0 @
b0 K
b0 S
b0 C
0)
b0 *
b0 /
b0 >
b10 -
#45000
16
13
b1 H
b10 G
1)
#50000
b11010 9
b11010 @
b11010 K
b11010 S
b11010 C
0)
b11010 *
b11010 /
b11010 >
b11 -
#55000
b11 G
06
03
1)
#60000
b0 9
b0 @
b0 K
b0 S
b0 C
0)
b0 *
b0 /
b0 >
b100 -
#65000
16
13
b10 H
b100 G
1)
#70000
b110 9
b110 @
b110 K
b110 S
b110 C
0)
b110 *
b110 /
b110 >
b101 -
#75000
b101 G
06
03
1)
#80000
b110111 9
b110111 @
b110111 K
b110111 S
b110111 C
0)
b110111 *
b110111 /
b110111 >
b110 -
#85000
b110111 4
b110111 ?
b110111 Q
b1101 8
16
13
b11 H
b110 G
b110111 #
b110111 0
b110111 5
b110111 M
b110111 O
1)
#90000
b1011100 9
b1011100 @
b1011100 K
b1011100 S
b1011100 C
0)
b1011100 *
b1011100 /
b1011100 >
b111 -
#95000
b0 4
b0 ?
b0 Q
b0 8
b0 #
b0 0
b0 5
b0 M
b0 O
b111 G
06
03
1)
#100000
b110000 9
b110000 @
b110000 K
b110000 S
b110000 C
0)
b110000 *
b110000 /
b110000 >
b1000 -
#105000
b110000 4
b110000 ?
b110000 Q
b1100 8
16
13
b100 H
b1000 G
b110000 #
b110000 0
b110000 5
b110000 M
b110000 O
1)
#110000
0)
b0 *
b0 /
b0 >
b1001 -
#115000
b0 9
b0 @
b0 K
b0 S
b0 C
b0 4
b0 ?
b0 Q
b0 8
b0 #
b0 0
b0 5
b0 M
b0 O
b1001 G
06
03
1)
#120000
b1111 9
b1111 @
b1111 K
b1111 S
b1111 C
0)
b1111 *
b1111 /
b1111 >
b1010 -
#125000
b1111 4
b1111 ?
b1111 Q
b11 8
16
13
b101 H
b1010 G
b1111 #
b1111 0
b1111 5
b1111 M
b1111 O
1)
#130000
b1000111 9
b1000111 @
b1000111 K
b1000111 S
b1000111 C
0)
b1000111 *
b1000111 /
b1000111 >
b1011 -
#135000
b0 4
b0 ?
b0 Q
b0 8
b0 #
b0 0
b0 5
b0 M
b0 O
b1011 G
06
03
1)
#140000
b0 9
b0 @
b0 K
b0 S
b0 C
0)
b0 *
b0 /
b0 >
b1100 -
#145000
16
13
b110 H
b1100 G
1)
#150000
0)
b1101 -
#155000
b1101 G
06
03
1)
#160000
0)
b1110 -
#165000
16
13
b111 H
b1110 G
1)
#170000
b1110 9
b1110 @
b1110 K
b1110 S
b1110 C
0)
b1110 *
b1110 /
b1110 >
b1111 -
#175000
b1111 G
06
03
1)
#180000
b0 9
b0 @
b0 K
b0 S
b0 C
0)
b0 *
b0 /
b0 >
b10000 -
#185000
16
13
b1000 H
b10000 G
1)
#190000
0)
b10001 -
#195000
b10001 G
06
03
1)
#200000
0)
b10010 -
#205000
16
13
b1001 H
b10010 G
1)
#210000
b110 9
b110 @
b110 K
b110 S
b110 C
0)
b110 *
b110 /
b110 >
b10011 -
#215000
b10011 G
06
03
1)
#220000
b101100 9
b101100 @
b101100 K
b101100 S
b101100 C
0)
b101100 *
b101100 /
b101100 >
b10100 -
#225000
b101100 4
b101100 ?
b101100 Q
b1011 8
16
13
b1010 H
b10100 G
b101100 #
b101100 0
b101100 5
b101100 M
b101100 O
1)
#230000
0)
b0 *
b0 /
b0 >
b10101 -
#235000
b0 9
b0 @
b0 K
b0 S
b0 C
b0 4
b0 ?
b0 Q
b0 8
b0 #
b0 0
b0 5
b0 M
b0 O
b10101 G
06
03
1)
#240000
0)
b10110 -
#245000
16
13
b1011 H
b10110 G
1)
#250000
b1000011 9
b1000011 @
b1000011 K
b1000011 S
b1000011 C
0)
b1000011 *
b1000011 /
b1000011 >
b10111 -
#255000
b10111 G
06
03
1)
#260000
b0 9
b0 @
b0 K
b0 S
b0 C
0)
b0 *
b0 /
b0 >
b11000 -
#265000
16
13
b1100 H
b11000 G
1)
#270000
b110110 9
b110110 @
b110110 K
b110110 S
b110110 C
0)
b110110 *
b110110 /
b110110 >
b11001 -
#275000
b11001 G
06
03
1)
#280000
b0 9
b0 @
b0 K
b0 S
b0 C
0)
b0 *
b0 /
b0 >
b11010 -
#285000
16
13
b1101 H
b11010 G
1)
#290000
0)
b11011 -
#295000
b1011110 9
b1011110 @
b1011110 K
b1011110 S
b1011110 C
b1011110 4
b1011110 ?
b1011110 Q
b1011110 1
b1011110 N
b1011110 T
b11011 G
06
b1 2
b1 F
b1 P
03
1)
#300000
0)
b101000 *
b101000 /
b101000 >
b11100 -
#305000
b10111 8
16
b0 2
b0 F
b0 P
b0 H
b1 J
b0 G
b1011110 #
b1011110 0
b1011110 5
b1011110 M
b1011110 O
1)
#310000
0)
b110110 *
b110110 /
b110110 >
b11101 -
#315000
b110110 9
b110110 @
b110110 K
b110110 S
b110110 C
b11010 4
b11010 ?
b11010 Q
b11010 1
b11010 N
b11010 T
b1 G
06
b1 2
b1 F
b1 P
1!
1)
#320000
b11010 9
b11010 @
b11010 K
b11010 S
b11010 C
0)
b0 *
b0 /
b0 >
b11110 -
#325000
b110 8
16
b0 2
b0 F
b0 P
0!
b1 H
b10 G
b11010 #
b11010 0
b11010 5
b11010 M
b11010 O
b1 .
1)
#330000
0)
b11010 *
b11010 /
b11010 >
b11111 -
#335000
b110 4
b110 ?
b110 Q
b110 1
b110 N
b110 T
b11 G
06
b1 2
b1 F
b1 P
1!
1)
#340000
b10011 9
b10011 @
b10011 K
b10011 S
b10011 C
0)
b10011 *
b10011 /
b10011 >
b100000 -
#345000
b10011 4
b10011 ?
b10011 Q
b100 8
16
b0 2
b0 F
b0 P
0!
b10 H
b100 G
b10011 #
b10011 0
b10011 5
b10011 M
b10011 O
b10 .
1)
#350000
0)
b1 *
b1 /
b1 >
b100001 -
#355000
b1011100 9
b1011100 @
b1011100 K
b1011100 S
b1011100 C
b1011100 4
b1011100 ?
b1011100 Q
b1011100 1
b1011100 N
b1011100 T
b101 G
06
b1 2
b1 F
b1 P
1!
1)
#360000
0)
b111001 *
b111001 /
b111001 >
b100010 -
#365000
b10111 8
16
b0 2
b0 F
b0 P
0!
b11 H
b110 G
b1011100 #
b1011100 0
b1011100 5
b1011100 M
b1011100 O
b11 .
1)
#370000
0)
b101110 *
b101110 /
b101110 >
b100011 -
#375000
b110000 9
b110000 @
b110000 K
b110000 S
b110000 C
b110000 4
b110000 ?
b110000 Q
b110000 1
b110000 N
b110000 T
b111 G
06
b1 2
b1 F
b1 P
1!
1)
#380000
b1010001 9
b1010001 @
b1010001 K
b1010001 S
b1010001 C
0)
b1010001 *
b1010001 /
b1010001 >
b100100 -
#385000
b1010001 4
b1010001 ?
b1010001 Q
b10100 8
16
b0 2
b0 F
b0 P
0!
b100 H
b1000 G
b1010001 #
b1010001 0
b1010001 5
b1010001 M
b1010001 O
b100 .
1)
#390000
0)
b100110 *
b100110 /
b100110 >
b100101 -
#395000
b1000111 9
b1000111 @
b1000111 K
b1000111 S
b1000111 C
b1000111 4
b1000111 ?
b1000111 Q
b1000111 1
b1000111 N
b1000111 T
b1001 G
06
b1 2
b1 F
b1 P
1!
1)
#400000
0)
b10000 *
b10000 /
b10000 >
b100110 -
#405000
b10001 8
16
b0 2
b0 F
b0 P
0!
b101 H
b1010 G
b1000111 #
b1000111 0
b1000111 5
b1000111 M
b1000111 O
b101 .
1)
#410000
0)
b111 *
b111 /
b111 >
b100111 -
#415000
b111 9
b111 @
b111 K
b111 S
b111 C
b0 4
b0 ?
b0 Q
b0 1
b0 N
b0 T
b1011 G
06
b1 2
b1 F
b1 P
1!
1)
#420000
b1011 9
b1011 @
b1011 K
b1011 S
b1011 C
0)
b1011 *
b1011 /
b1011 >
b101000 -
#425000
b1011 4
b1011 ?
b1011 Q
b10 8
16
b0 2
b0 F
b0 P
0!
b110 H
b1100 G
b1011 #
b1011 0
b1011 5
b1011 M
b1011 O
b110 .
1)
#430000
b1000000 9
b1000000 @
b1000000 K
b1000000 S
b1000000 C
0)
b1000000 *
b1000000 /
b1000000 >
b101001 -
#435000
b10000 8
b1110 4
b1110 ?
b1110 Q
b1110 1
b1110 N
b1110 T
b1000000 #
b1000000 0
b1000000 5
b1000000 M
b1000000 O
b1101 G
06
b1 2
b1 F
b1 P
1!
1)
#440000
b1000111 9
b1000111 @
b1000111 K
b1000111 S
b1000111 C
0)
b1000111 *
b1000111 /
b1000111 >
b101010 -
#445000
b1000111 4
b1000111 ?
b1000111 Q
b10001 8
16
b0 2
b0 F
b0 P
0!
b111 H
b1110 G
b1000111 #
b1000111 0
b1000111 5
b1000111 M
b1000111 O
b111 .
1)
#450000
0)
b111010 *
b111010 /
b111010 >
b101011 -
#455000
b111010 9
b111010 @
b111010 K
b111010 S
b111010 C
b0 4
b0 ?
b0 Q
b0 1
b0 N
b0 T
b1111 G
06
b1 2
b1 F
b1 P
1!
1)
#460000
b0 9
b0 @
b0 K
b0 S
b0 C
0)
b0 *
b0 /
b0 >
b101100 -
#465000
b0 8
16
b0 2
b0 F
b0 P
0!
b1000 H
b10000 G
b0 #
b0 0
b0 5
b0 M
b0 O
b1000 .
1)
#470000
b10111 9
b10111 @
b10111 K
b10111 S
b10111 C
0)
b10111 *
b10111 /
b10111 >
b101101 -
#475000
b101 8
b110 4
b110 ?
b110 Q
b110 1
b110 N
b110 T
b10111 #
b10111 0
b10111 5
b10111 M
b10111 O
b10001 G
06
b1 2
b1 F
b1 P
1!
1)
#480000
b110 9
b110 @
b110 K
b110 S
b110 C
0)
b0 *
b0 /
b0 >
b101110 -
#485000
b1 8
16
b0 2
b0 F
b0 P
0!
b1001 H
b10010 G
b110 #
b110 0
b110 5
b110 M
b110 O
b1001 .
1)
#490000
0)
b101111 -
#495000
b101100 9
b101100 @
b101100 K
b101100 S
b101100 C
b101100 4
b101100 ?
b101100 Q
b101100 1
b101100 N
b101100 T
b10011 G
06
b1 2
b1 F
b1 P
1!
1)
#500000
0)
b1111 *
b1111 /
b1111 >
b110000 -
#505000
b1011 8
16
b0 2
b0 F
b0 P
0!
b1010 H
b10100 G
b101100 #
b101100 0
b101100 5
b101100 M
b101100 O
b1010 .
1)
#510000
0)
b10011 *
b10011 /
b10011 >
b110001 -
#515000
b1000011 9
b1000011 @
b1000011 K
b1000011 S
b1000011 C
b1000011 4
b1000011 ?
b1000011 Q
b1000011 1
b1000011 N
b1000011 T
b10101 G
06
b1 2
b1 F
b1 P
1!
1)
#520000
0)
b1000011 *
b1000011 /
b1000011 >
b110010 -
#525000
b10000 8
16
b0 2
b0 F
b0 P
0!
b1011 H
b10110 G
b1000011 #
b1000011 0
b1000011 5
b1000011 M
b1000011 O
b1011 .
1)
#530000
0)
b101110 *
b101110 /
b101110 >
b110011 -
#535000
b110110 9
b110110 @
b110110 K
b110110 S
b110110 C
b110110 4
b110110 ?
b110110 Q
b110110 1
b110110 N
b110110 T
b10111 G
06
b1 2
b1 F
b1 P
1!
1)
#540000
0)
b0 *
b0 /
b0 >
b110100 -
#545000
b1101 8
16
b0 2
b0 F
b0 P
0!
b1100 H
b11000 G
b110110 #
b110110 0
b110110 5
b110110 M
b110110 O
b1100 .
1)
#550000
0)
b110101 -
#555000
b0 9
b0 @
b0 K
b0 S
b0 C
b0 4
b0 ?
b0 Q
b0 1
b0 N
b0 T
b11001 G
06
b1 2
b1 F
b1 P
1!
1)
#560000
b101101 9
b101101 @
b101101 K
b101101 S
b101101 C
0)
b101101 *
b101101 /
b101101 >
b110110 -
#565000
b101101 4
b101101 ?
b101101 Q
b1011 8
16
b0 2
b0 F
b0 P
0!
b1101 H
b11010 G
b101101 #
b101101 0
b101101 5
b101101 M
b101101 O
b1101 .
1)
#570000
0)
b0 *
b0 /
b0 >
b110111 -
#575000
b0 9
b0 @
b0 K
b0 S
b0 C
b0 4
b0 ?
b0 Q
b1011110 1
b1011110 N
b1011110 T
b11011 G
06
b10 2
b10 F
b10 P
17
1!
1)
#580000
b1010011 9
b1010011 @
b1010011 K
b1010011 S
b1010011 C
0)
b1010011 *
b1010011 /
b1010011 >
b111000 -
#585000
b1010011 4
b1010011 ?
b1010011 Q
b10100 8
16
b0 2
b0 F
b0 P
13
07
0!
b10 I
b0 H
b0 G
b0 J
b1010011 #
b1010011 0
b1010011 5
b1010011 M
b1010011 O
b1110 .
1)
#590000
0)
b0 *
b0 /
b0 >
b111001 -
#595000
b0 9
b0 @
b0 K
b0 S
b0 C
b0 4
b0 ?
b0 Q
b0 8
b11010 1
b11010 N
b11010 T
b0 #
b0 0
b0 5
b0 M
b0 O
b1 G
06
03
1)
#600000
b100 9
b100 @
b100 K
b100 S
b100 C
0)
b100 *
b100 /
b100 >
b111010 -
#605000
b100 4
b100 ?
b100 Q
b1 8
16
13
b1 H
b10 G
b100 #
b100 0
b100 5
b100 M
b100 O
1)
#610000
0)
b0 *
b0 /
b0 >
b111011 -
#615000
b0 9
b0 @
b0 K
b0 S
b0 C
b0 4
b0 ?
b0 Q
b0 8
b10011 1
b10011 N
b10011 T
b0 #
b0 0
b0 5
b0 M
b0 O
b11 G
06
03
1)
#620000
b111010 9
b111010 @
b111010 K
b111010 S
b111010 C
0)
b111010 *
b111010 /
b111010 >
b111100 -
#625000
b111010 4
b111010 ?
b111010 Q
b1110 8
16
13
b10 H
b100 G
b111010 #
b111010 0
b111010 5
b111010 M
b111010 O
1)
#630000
0)
b11000 *
b11000 /
b11000 >
b111101 -
#635000
b11000 9
b11000 @
b11000 K
b11000 S
b11000 C
b0 4
b0 ?
b0 Q
b0 8
b1011100 1
b1011100 N
b1011100 T
b0 #
b0 0
b0 5
b0 M
b0 O
b101 G
06
03
1)
#640000
b0 9
b0 @
b0 K
b0 S
b0 C
0)
b0 *
b0 /
b0 >
b111110 -
#645000
16
13
b11 H
b110 G
1)
#650000
0)
b111111 -
#655000
b1010001 1
b1010001 N
b1010001 T
b111 G
06
03
1)
#660000
b101110 9
b101110 @
b101110 K
b101110 S
b101110 C
0)
b101110 *
b101110 /
b101110 >
b1000000 -
#665000
b101110 4
b101110 ?
b101110 Q
b1011 8
16
13
b100 H
b1000 G
b101110 #
b101110 0
b101110 5
b101110 M
b101110 O
1)
#670000
0)
b11010 *
b11010 /
b11010 >
b1000001 -
#675000
b11010 9
b11010 @
b11010 K
b11010 S
b11010 C
b0 4
b0 ?
b0 Q
b0 8
b1000111 1
b1000111 N
b1000111 T
b0 #
b0 0
b0 5
b0 M
b0 O
b1001 G
06
03
1)
